opentraveldata/__init__.py
opentraveldata/csvwriter.py
opentraveldata/opentraveldata.py
opentraveldata-0.0.9.post3.dist-info/METADATA
opentraveldata-0.0.9.post3.dist-info/WHEEL
opentraveldata-0.0.9.post3.dist-info/top_level.txt
opentraveldata-0.0.9.post3.dist-info/RECORD
