Metadata-Version: 2.1
Name: opentraveldata
Version: 0.0.9.post3
Summary: Simple Python wrapper for OpenTravelata (OPTD)
Author-email: Denis Arnaud <denis.arnaud_fedora@m4x.org>
Project-URL: homepage, https://github.com/opentraveldata/python-opentraveldata
Project-URL: repository, https://github.com/opentraveldata/python-opentraveldata
Project-URL: documentation, https://github.com/opentraveldata/python-opentraveldata
Keywords: packaging,package,dependency,pyproject.toml,api,python,optd,opentraveldata
Classifier: Topic :: Software Development
Classifier: Programming Language :: Python :: 3
Classifier: License :: OSI Approved :: MIT License
Classifier: Operating System :: OS Independent
